SSVD663/__init__.py
SSVD663-1.2.dist-info/LICENSE.txt
SSVD663-1.2.dist-info/METADATA
SSVD663-1.2.dist-info/WHEEL
SSVD663-1.2.dist-info/top_level.txt
SSVD663-1.2.dist-info/RECORD
