Metadata-Version: 2.1
Name: SSVD663
Version: 1.2
Summary: A python relization of sparse singular value decomposition algorithm. It is based on paper "Biclustering via Sparse Singular Value Decomposition" written by Mihee Lee, Haipeng Shen, Jianhua Z. Huang, and J. S. Marron.
Home-page: https://github.com/Yutong-Z/Sparse-SVD-Algorithm.git
Author: Jiaxi Yin, Yutong Zhang
Author-email: jy280@duke.edu,yz566@duke.edu
License: MIT
Platform: UNKNOWN
Requires-Dist: numpy
Requires-Dist: multiprocessing
Requires-Dist: functools
